bseq/__init__.py
bseq/alignment.py
bseq/formatter.py
bseq/marker.py
bseq/reader.py
bseq/sequence.py
bseq-1.0.1.dist-info/LICENSE
bseq-1.0.1.dist-info/METADATA
bseq-1.0.1.dist-info/WHEEL
bseq-1.0.1.dist-info/top_level.txt
bseq-1.0.1.dist-info/RECORD
