Metadata-Version: 2.1
Name: bseq
Version: 1.0.1
Summary: Python package for handling biological sequences and alignments
Home-page: https://bitbucket.org/nigevogen/bseq
Author: Kent Kawashima
Author-email: kentkawashima@nig.ac.jp
License: UNKNOWN
Platform: UNKNOWN
Classifier: Programming Language :: Python :: 3
Classifier: License :: OSI Approved :: Apache Software License
Classifier: Operating System :: OS Independent
Classifier: Topic :: Scientific/Engineering :: Bio-Informatics
Requires-Dist: numpy
Requires-Dist: nose
